rwskit/__init__.py
rwskit/benchmarking.py
rwskit/cli.py
rwskit/collections_.py
rwskit/config.py
rwskit/dataclasses_.py
rwskit/exceptions.py
rwskit/files.py
rwskit/hash.py
rwskit/io_.py
rwskit/logging.py
rwskit/numeric.py
rwskit/numpy.py
rwskit/pandas.py
rwskit/resources_.py
rwskit/strings_.py
rwskit/transliterate_accent.rules
rwskit/types_.py
rwskit/notebooks/__init__.py
rwskit/sqlalchemy/__init__.py
rwskit/sqlalchemy/base.py
rwskit/sqlalchemy/cache.py
rwskit/sqlalchemy/config.py
rwskit/sqlalchemy/engine.py
rwskit/sqlalchemy/expressions.py
rwskit/sqlalchemy/repository.py
rwskit/stats/__init__.py
rwskit/stats/bayesian/__init__.py
rwskit/stats/bayesian/ttest.py
rwskit-0.30.4.dist-info/licenses/LICENSE.md
rwskit-0.30.4.dist-info/METADATA
rwskit-0.30.4.dist-info/WHEEL
rwskit-0.30.4.dist-info/top_level.txt
rwskit-0.30.4.dist-info/RECORD
