Metadata-Version: 2.4
Name: rwskit
Version: 0.30.4
Summary: Utility methods I've found useful.
Author-email: Reid Swanson <reid@reidswanson.com>
License: 3-Clause BSD License
Project-URL: Homepage, https://bitbucket.org/reidswanson/rwskit
Project-URL: Documentation, https://rwskit.readthedocs.io/en/latest
License-File: LICENSE.md
Requires-Dist: black
Requires-Dist: humanize
Requires-Dist: icontract
Requires-Dist: isort
Requires-Dist: msgspec
Requires-Dist: numpy
Requires-Dist: pydantic
Requires-Dist: pympler
Requires-Dist: pyyaml
Requires-Dist: pyyaml-include
Requires-Dist: ruff
Requires-Dist: xxhash
Requires-Dist: yamlable
Provides-Extra: bayes
Requires-Dist: arviz; extra == "bayes"
Requires-Dist: seaborn; extra == "bayes"
Requires-Dist: aesara; extra == "bayes"
Requires-Dist: pymc; extra == "bayes"
Provides-Extra: numpy
Requires-Dist: numpy; extra == "numpy"
Requires-Dist: numpy-indexed; extra == "numpy"
Requires-Dist: xarray; extra == "numpy"
Provides-Extra: pandas
Requires-Dist: pandas; extra == "pandas"
Provides-Extra: sqlalchemy
Requires-Dist: sqlalchemy; extra == "sqlalchemy"
Provides-Extra: benchmarking
Requires-Dist: numpy; extra == "benchmarking"
Requires-Dist: pandas; extra == "benchmarking"
Requires-Dist: plotnine[all]; extra == "benchmarking"
Requires-Dist: tqdm; extra == "benchmarking"
Provides-Extra: notebooks
Requires-Dist: memory-profiler; extra == "notebooks"
Requires-Dist: numpy; extra == "notebooks"
Requires-Dist: numpy-indexed; extra == "notebooks"
Requires-Dist: numpy-groupies; extra == "notebooks"
Requires-Dist: pandas; extra == "notebooks"
Requires-Dist: perfplot; extra == "notebooks"
Requires-Dist: pysort; extra == "notebooks"
Provides-Extra: bump2version
Requires-Dist: bump-my-version; extra == "bump2version"
Provides-Extra: documentation
Requires-Dist: livereload; extra == "documentation"
Requires-Dist: six; extra == "documentation"
Requires-Dist: sphinx; extra == "documentation"
Requires-Dist: sphinx-autoapi; extra == "documentation"
Requires-Dist: sphinx_rtd_theme; extra == "documentation"
Provides-Extra: testing
Requires-Dist: aiosqlite; extra == "testing"
Requires-Dist: asyncpg; extra == "testing"
Requires-Dist: hypothesis; extra == "testing"
Requires-Dist: numpy; extra == "testing"
Requires-Dist: psycopg[binary,pool]; extra == "testing"
Requires-Dist: pytest; extra == "testing"
Requires-Dist: pytest-asyncio; extra == "testing"
Requires-Dist: pytest-cov; extra == "testing"
Requires-Dist: pytest_postgresql; extra == "testing"
Provides-Extra: all
Requires-Dist: rwskit[bayes,benchmarking,bump2version,cli,documentation,notebooks,numpy,pandas,sqlalchemy,testing]; extra == "all"
Dynamic: license-file
